widowx_env/__init__.py
widowx_env-0.0.2.dist-info/LICENSE
widowx_env-0.0.2.dist-info/METADATA
widowx_env-0.0.2.dist-info/WHEEL
widowx_env-0.0.2.dist-info/top_level.txt
widowx_env-0.0.2.dist-info/RECORD
